ai_fuzzy_rec/__init__.py
ai_fuzzy_rec/ai_fuzzy_rec.py
ai_fuzzy_rec-0.1.0.dist-info/LICENSE
ai_fuzzy_rec-0.1.0.dist-info/METADATA
ai_fuzzy_rec-0.1.0.dist-info/WHEEL
ai_fuzzy_rec-0.1.0.dist-info/RECORD
