Metadata-Version: 2.3
Name: ai-fuzzy-rec
Version: 0.1.0
Summary: An AI-enhanced fuzzy logic-based item recommendation system for SQLite databases.
License: MIT
Keywords: fuzzy logic,recommender system,ai,sqlite,recommendations
Author: fadedreams7
Author-email: fadedreams7@gmail.com
Requires-Python: >=3.6
Classifier: Environment :: Console
Classifier: License :: OSI Approved :: MIT License
Classifier: Operating System :: OS Independent
Classifier: Programming Language :: Python :: 3
Classifier: Programming Language :: Python :: 3.6
Classifier: Programming Language :: Python :: 3.7
Classifier: Programming Language :: Python :: 3.8
Classifier: Programming Language :: Python :: 3.9
Classifier: Programming Language :: Python :: 3.10
Classifier: Programming Language :: Python :: 3.11
Classifier: Programming Language :: Python :: 3.12
Classifier: Programming Language :: Python :: 3.13
Classifier: Topic :: Scientific/Engineering :: Artificial Intelligence
Classifier: Topic :: Software Development :: Libraries :: Python Modules
Requires-Dist: numpy (>=1.25.0)
Requires-Dist: packaging (>=21.3)
Requires-Dist: pandas (>=2.0.0)
Requires-Dist: scikit-fuzzy (>=0.4.2)
Requires-Dist: scipy (>=1.10.0)
Project-URL: Homepage, https://github.com/fadedreams/ai-fuzzy-rec
Project-URL: Repository, https://github.com/fadedreams/ai-fuzzy-rec
